psql_query_builder/__init__.py
psql_query_builder/__main__.py
psql_query_builder/cli.py
psql_query_builder/db_agent.py
psql_query_builder/error_handler.py
psql_query_builder/langchain_integration.py
psql_query_builder/prompt.py
psql_query_builder/query_builder.py
psql_query_builder/query_generator.py
psql_query_builder/schema_cache.py
psql_query_builder-0.2.0.dist-info/licenses/LICENSE
psql_query_builder-0.2.0.dist-info/METADATA
psql_query_builder-0.2.0.dist-info/WHEEL
psql_query_builder-0.2.0.dist-info/entry_points.txt
psql_query_builder-0.2.0.dist-info/top_level.txt
psql_query_builder-0.2.0.dist-info/RECORD
