Metadata-Version: 2.4
Name: psql-query-builder
Version: 0.2.0
Summary: Generate PostgreSQL queries from natural language using AI
Home-page: https://github.com/celestialtaha/psql-query-builder
Author: Taha
Author-email: tahasamavati11@yahoo.com
Classifier: Programming Language :: Python :: 3
Classifier: Programming Language :: Python :: 3.8
Classifier: Programming Language :: Python :: 3.9
Classifier: Programming Language :: Python :: 3.10
Classifier: Programming Language :: Python :: 3.11
Classifier: Programming Language :: Python :: 3.12
Classifier: License :: OSI Approved :: MIT License
Classifier: Operating System :: OS Independent
Classifier: Topic :: Database
Classifier: Topic :: Utilities
Requires-Python: >=3.8
License-File: LICENSE
Requires-Dist: loguru==0.7.2
Requires-Dist: openai==1.79.0
Requires-Dist: psycopg2_binary==2.9.10
Requires-Dist: setuptools==67.8.0
Requires-Dist: tabulate==0.9.0
Dynamic: author
Dynamic: author-email
Dynamic: classifier
Dynamic: description
Dynamic: description-content-type
Dynamic: home-page
Dynamic: license-file
Dynamic: requires-dist
Dynamic: requires-python
Dynamic: summary
